mqtt_framework/__init__.py
mqtt_framework/_topic_handler.py
mqtt_framework/client.py
mqtt_framework/settings.py
python_mqtt_framework-0.0.5.dist-info/METADATA
python_mqtt_framework-0.0.5.dist-info/WHEEL
python_mqtt_framework-0.0.5.dist-info/top_level.txt
python_mqtt_framework-0.0.5.dist-info/RECORD
