Metadata-Version: 2.1
Name: python-mqtt-framework
Version: 0.0.5
Summary: An opinionated framework to handle MQTT communication in Python.
Home-page: https://github.com/jourdanrodrigues/python-mqtt-framework
Author: Jourdan Rodrigues
Author-email: thiagojourdan@gmail.com
Classifier: Development Status :: 3 - Alpha
Classifier: Environment :: Web Environment
Classifier: Intended Audience :: Developers
Classifier: License :: OSI Approved :: MIT License
Classifier: Operating System :: OS Independent
Classifier: Programming Language :: Python :: 3
Classifier: Programming Language :: Python :: 3.8
Classifier: Programming Language :: Python :: 3.9
Classifier: Programming Language :: Python :: 3.10
Classifier: Programming Language :: Python :: 3.11
Classifier: Programming Language :: Python :: 3.12
Classifier: Topic :: Internet
Classifier: Topic :: Internet :: WWW/HTTP
Classifier: Topic :: Internet :: WWW/HTTP :: Dynamic Content
Classifier: Topic :: Software Development :: Libraries :: Application Frameworks
Classifier: Topic :: Software Development :: Libraries :: Python Modules
Requires-Python: >=3.8
Requires-Dist: paho-mqtt >=2.0
Provides-Extra: dev
Requires-Dist: django-cache-url >=3.4.5 ; extra == 'dev'
Requires-Dist: djangorestframework >=3.15 ; extra == 'dev'
Requires-Dist: pydantic >=2.7.1 ; extra == 'dev'
Requires-Dist: pylibmc >=1.6.3 ; extra == 'dev'
Requires-Dist: tox >=4.15.0 ; extra == 'dev'
Requires-Dist: coverage >=7.5.1 ; extra == 'dev'
